autogluon.common-1.4.0-py3.9-nspkg.pth
autogluon/common/__init__.py
autogluon/common/dataset.py
autogluon/common/space.py
autogluon/common/version.py
autogluon/common/features/__init__.py
autogluon/common/features/feature_metadata.py
autogluon/common/features/infer_types.py
autogluon/common/features/types.py
autogluon/common/loaders/__init__.py
autogluon/common/loaders/_utils.py
autogluon/common/loaders/load_json.py
autogluon/common/loaders/load_pd.py
autogluon/common/loaders/load_pkl.py
autogluon/common/loaders/load_pointer.py
autogluon/common/loaders/load_s3.py
autogluon/common/loaders/load_str.py
autogluon/common/loaders/load_zip.py
autogluon/common/model_filter/__init__.py
autogluon/common/model_filter/_model_filter.py
autogluon/common/savers/__init__.py
autogluon/common/savers/save_json.py
autogluon/common/savers/save_pd.py
autogluon/common/savers/save_pkl.py
autogluon/common/savers/save_pointer.py
autogluon/common/savers/save_str.py
autogluon/common/utils/__init__.py
autogluon/common/utils/compression_utils.py
autogluon/common/utils/context.py
autogluon/common/utils/cpu_utils.py
autogluon/common/utils/deprecated_utils.py
autogluon/common/utils/distribute_utils.py
autogluon/common/utils/file_utils.py
autogluon/common/utils/hyperparameter_utils.py
autogluon/common/utils/lite.py
autogluon/common/utils/log_utils.py
autogluon/common/utils/multiprocessing_utils.py
autogluon/common/utils/nvutil.py
autogluon/common/utils/pandas_utils.py
autogluon/common/utils/path_converter.py
autogluon/common/utils/resource_utils.py
autogluon/common/utils/s3_utils.py
autogluon/common/utils/simulation_utils.py
autogluon/common/utils/system_info.py
autogluon/common/utils/try_import.py
autogluon/common/utils/utils.py
autogluon.common-1.4.0.dist-info/LICENSE
autogluon.common-1.4.0.dist-info/METADATA
autogluon.common-1.4.0.dist-info/NOTICE
autogluon.common-1.4.0.dist-info/WHEEL
autogluon.common-1.4.0.dist-info/namespace_packages.txt
autogluon.common-1.4.0.dist-info/top_level.txt
autogluon.common-1.4.0.dist-info/zip-safe
autogluon.common-1.4.0.dist-info/RECORD
