Metadata-Version: 2.1
Name: autogluon.common
Version: 1.4.0
Summary: Fast and Accurate ML in 3 Lines of Code
Home-page: https://github.com/autogluon/autogluon
Author: AutoGluon Community
License: Apache-2.0
Project-URL: Documentation, https://auto.gluon.ai
Project-URL: Bug Reports, https://github.com/autogluon/autogluon/issues
Project-URL: Source, https://github.com/autogluon/autogluon/
Project-URL: Contribute!, https://github.com/autogluon/autogluon/blob/master/CONTRIBUTING.md
Platform: UNKNOWN
Classifier: Development Status :: 5 - Production/Stable
Classifier: Intended Audience :: Education
Classifier: Intended Audience :: Developers
Classifier: Intended Audience :: Science/Research
Classifier: Intended Audience :: Customer Service
Classifier: Intended Audience :: Financial and Insurance Industry
Classifier: Intended Audience :: Healthcare Industry
Classifier: Intended Audience :: Telecommunications Industry
Classifier: License :: OSI Approved :: Apache Software License
Classifier: Operating System :: MacOS
Classifier: Operating System :: Microsoft :: Windows
Classifier: Operating System :: POSIX
Classifier: Operating System :: Unix
Classifier: Programming Language :: Python :: 3
Classifier: Programming Language :: Python :: 3.9
Classifier: Programming Language :: Python :: 3.10
Classifier: Programming Language :: Python :: 3.11
Classifier: Programming Language :: Python :: 3.12
Classifier: Topic :: Software Development
Classifier: Topic :: Scientific/Engineering :: Artificial Intelligence
Classifier: Topic :: Scientific/Engineering :: Information Analysis
Classifier: Topic :: Scientific/Engineering :: Image Recognition
Requires-Python: >=3.9, <3.13
License-File: ../LICENSE
License-File: ../NOTICE
Requires-Dist: numpy<2.4.0,>=1.25.0
Requires-Dist: pandas<2.4.0,>=2.0.0
Requires-Dist: pyarrow<21.0.0,>=7.0.0
Requires-Dist: boto3<2,>=1.10
Requires-Dist: psutil<7.1.0,>=5.7.3
Requires-Dist: tqdm<5,>=4.38
Requires-Dist: requests
Requires-Dist: joblib<1.7,>=1.2
Provides-Extra: tests
Requires-Dist: pytest-mypy; extra == "tests"
Requires-Dist: types-setuptools; extra == "tests"
Requires-Dist: pytest; extra == "tests"
Requires-Dist: types-requests; extra == "tests"
